{"title": "Quelvhar", "id": "tg-1252197925602197505", "net.maunium.telegram.pack": {"short_name": "QuelvhartheDragon", "hash": "432421879"}, "stickers": [{"body": "😀", "url": "mxc://bark.lgbt/kvoptASqRcmfrMvhHvZgufHY", "info": {"w": 256, "h": 256, "size": 239023, "mimetype": "image/png", "thumbnail_url": "mxc://bark.lgbt/kvoptASqRcmfrMvhHvZgufHY", "thumbnail_info": {"w": 256, "h": 256, "size": 239023, "mimetype": "image/png"}}, "msgtype": "m.sticker", "id": "tg-1252197925602197514", "net.maunium.telegram.sticker": {"pack": {"id": "1252197925602197505", "short_name": "QuelvhartheDragon"}, "id": "1252197925602197514", "emoticons": ["😀"]}}, {"body": "🐊", "url": "mxc://bark.lgbt/tzEcVtkUHWyfTSieQHLuiKUR", "info": {"w": 256, "h": 256, "size": 240519, "mimetype": "image/png", "thumbnail_url": "mxc://bark.lgbt/tzEcVtkUHWyfTSieQHLuiKUR", "thumbnail_info": {"w": 256, "h": 256, "size": 240519, "mimetype": "image/png"}}, "msgtype": "m.sticker", "id": "tg-1252197925602197505", "net.maunium.telegram.sticker": {"pack": {"id": "1252197925602197505", "short_name": "QuelvhartheDragon"}, "id": "1252197925602197505", "emoticons": ["🐊"]}}, {"body": "👍", "url": "mxc://bark.lgbt/iCqCTaNYOknIHLfksVJBHDiK", "info": {"w": 256, "h": 256, "size": 129886, "mimetype": "image/png", "thumbnail_url": "mxc://bark.lgbt/iCqCTaNYOknIHLfksVJBHDiK", "thumbnail_info": {"w": 256, "h": 256, "size": 129886, "mimetype": "image/png"}}, "msgtype": "m.sticker", "id": "tg-1252197925602197506", "net.maunium.telegram.sticker": {"pack": {"id": "1252197925602197505", "short_name": "QuelvhartheDragon"}, "id": "1252197925602197506", "emoticons": ["👍"]}}, {"body": "👎", "url": "mxc://bark.lgbt/StMSgoZbrVajUItkRfHsuImG", "info": {"w": 256, "h": 256, "size": 141467, "mimetype": "image/png", "thumbnail_url": "mxc://bark.lgbt/StMSgoZbrVajUItkRfHsuImG", "thumbnail_info": {"w": 256, "h": 256, "size": 141467, "mimetype": "image/png"}}, "msgtype": "m.sticker", "id": "tg-1252197925602197507", "net.maunium.telegram.sticker": {"pack": {"id": "1252197925602197505", "short_name": "QuelvhartheDragon"}, "id": "1252197925602197507", "emoticons": ["👎"]}}, {"body": "👥", "url": "mxc://bark.lgbt/pdmCysebgdtrOpjocHHJZspG", "info": {"w": 256, "h": 256, "size": 173950, "mimetype": "image/png", "thumbnail_url": "mxc://bark.lgbt/pdmCysebgdtrOpjocHHJZspG", "thumbnail_info": {"w": 256, "h": 256, "size": 173950, "mimetype": "image/png"}}, "msgtype": "m.sticker", "id": "tg-1252197925602197508", "net.maunium.telegram.sticker": {"pack": {"id": "1252197925602197505", "short_name": "QuelvhartheDragon"}, "id": "1252197925602197508", "emoticons": ["👥"]}}, {"body": "😊", "url": "mxc://bark.lgbt/miOhCHhctNokVbhiqMYThhLg", "info": {"w": 256, "h": 256, "size": 230602, "mimetype": "image/png", "thumbnail_url": "mxc://bark.lgbt/miOhCHhctNokVbhiqMYThhLg", "thumbnail_info": {"w": 256, "h": 256, "size": 230602, "mimetype": "image/png"}}, "msgtype": "m.sticker", "id": "tg-4961104938219340787", "net.maunium.telegram.sticker": {"pack": {"id": "1252197925602197505", "short_name": "QuelvhartheDragon"}, "id": "4961104938219340787", "emoticons": ["😊"]}}, {"body": "🪑", "url": "mxc://bark.lgbt/ahQbqMKGSqLDXjNprurkTFyC", "info": {"w": 256, "h": 256, "size": 134653, "mimetype": "image/png", "thumbnail_url": "mxc://bark.lgbt/ahQbqMKGSqLDXjNprurkTFyC", "thumbnail_info": {"w": 256, "h": 256, "size": 134653, "mimetype": "image/png"}}, "msgtype": "m.sticker", "id": "tg-4961079275789747609", "net.maunium.telegram.sticker": {"pack": {"id": "1252197925602197505", "short_name": "QuelvhartheDragon"}, "id": "4961079275789747609", "emoticons": ["🪑"]}}, {"body": "👅", "url": "mxc://bark.lgbt/fvIbBFiRDpRkzKJdeuFWemVf", "info": {"w": 256, "h": 256, "size": 148793, "mimetype": "image/png", "thumbnail_url": "mxc://bark.lgbt/fvIbBFiRDpRkzKJdeuFWemVf", "thumbnail_info": {"w": 256, "h": 256, "size": 148793, "mimetype": "image/png"}}, "msgtype": "m.sticker", "id": "tg-4963154466548220557", "net.maunium.telegram.sticker": {"pack": {"id": "1252197925602197505", "short_name": "QuelvhartheDragon"}, "id": "4963154466548220557", "emoticons": ["👅"]}}, {"body": "👨‍❤️‍👨", "url": "mxc://bark.lgbt/kkKcvfXtyNQknONkJWajDode", "info": {"w": 256, "h": 256, "size": 213255, "mimetype": "image/png", "thumbnail_url": "mxc://bark.lgbt/kkKcvfXtyNQknONkJWajDode", "thumbnail_info": {"w": 256, "h": 256, "size": 213255, "mimetype": "image/png"}}, "msgtype": "m.sticker", "id": "tg-1252197925602197588", "net.maunium.telegram.sticker": {"pack": {"id": "1252197925602197505", "short_name": "QuelvhartheDragon"}, "id": "1252197925602197588", "emoticons": ["👨‍❤‍👨"]}}, {"body": "💋", "url": "mxc://bark.lgbt/oPnvrVNLfdGSTMCjkQbhZrLR", "info": {"w": 256, "h": 256, "size": 183406, "mimetype": "image/png", "thumbnail_url": "mxc://bark.lgbt/oPnvrVNLfdGSTMCjkQbhZrLR", "thumbnail_info": {"w": 256, "h": 256, "size": 183406, "mimetype": "image/png"}}, "msgtype": "m.sticker", "id": "tg-1252197925602197587", "net.maunium.telegram.sticker": {"pack": {"id": "1252197925602197505", "short_name": "QuelvhartheDragon"}, "id": "1252197925602197587", "emoticons": ["👅", "💋"]}}, {"body": "🍟", "url": "mxc://bark.lgbt/XuzjhLabeFVlZmmXqkweaIpY", "info": {"w": 256, "h": 256, "size": 259720, "mimetype": "image/png", "thumbnail_url": "mxc://bark.lgbt/XuzjhLabeFVlZmmXqkweaIpY", "thumbnail_info": {"w": 256, "h": 256, "size": 259720, "mimetype": "image/png"}}, "msgtype": "m.sticker", "id": "tg-1252197925602197509", "net.maunium.telegram.sticker": {"pack": {"id": "1252197925602197505", "short_name": "QuelvhartheDragon"}, "id": "1252197925602197509", "emoticons": ["🍟"]}}, {"body": "🌶", "url": "mxc://bark.lgbt/ribKDoKSCRyXzmjLSkdGIpdA", "info": {"w": 256, "h": 256, "size": 165781, "mimetype": "image/png", "thumbnail_url": "mxc://bark.lgbt/ribKDoKSCRyXzmjLSkdGIpdA", "thumbnail_info": {"w": 256, "h": 256, "size": 165781, "mimetype": "image/png"}}, "msgtype": "m.sticker", "id": "tg-1252197925602197511", "net.maunium.telegram.sticker": {"pack": {"id": "1252197925602197505", "short_name": "QuelvhartheDragon"}, "id": "1252197925602197511", "emoticons": ["🌶"]}}, {"body": "👑", "url": "mxc://bark.lgbt/QwRXRPvxULYDEdmarPtduqlY", "info": {"w": 256, "h": 256, "size": 159649, "mimetype": "image/png", "thumbnail_url": "mxc://bark.lgbt/QwRXRPvxULYDEdmarPtduqlY", "thumbnail_info": {"w": 256, "h": 256, "size": 159649, "mimetype": "image/png"}}, "msgtype": "m.sticker", "id": "tg-5125205777354588826", "net.maunium.telegram.sticker": {"pack": {"id": "1252197925602197505", "short_name": "QuelvhartheDragon"}, "id": "5125205777354588826", "emoticons": ["👑"]}}, {"body": "🌑", "url": "mxc://bark.lgbt/tqXCLcCaSUHycxBoCFmDroTF", "info": {"w": 256, "h": 256, "size": 157628, "mimetype": "image/png", "thumbnail_url": "mxc://bark.lgbt/tqXCLcCaSUHycxBoCFmDroTF", "thumbnail_info": {"w": 256, "h": 256, "size": 157628, "mimetype": "image/png"}}, "msgtype": "m.sticker", "id": "tg-1252197925602197519", "net.maunium.telegram.sticker": {"pack": {"id": "1252197925602197505", "short_name": "QuelvhartheDragon"}, "id": "1252197925602197519", "emoticons": ["🌑"]}}, {"body": "🌈", "url": "mxc://bark.lgbt/aXLbcEKzuxijMjPpiTAKXNgB", "info": {"w": 256, "h": 256, "size": 172973, "mimetype": "image/png", "thumbnail_url": "mxc://bark.lgbt/aXLbcEKzuxijMjPpiTAKXNgB", "thumbnail_info": {"w": 256, "h": 256, "size": 172973, "mimetype": "image/png"}}, "msgtype": "m.sticker", "id": "tg-1252197925602197520", "net.maunium.telegram.sticker": {"pack": {"id": "1252197925602197505", "short_name": "QuelvhartheDragon"}, "id": "1252197925602197520", "emoticons": ["🌈"]}}, {"body": "❤️", "url": "mxc://bark.lgbt/rqpOLhmTFquYDIMiISrdRFTt", "info": {"w": 256, "h": 256, "size": 145697, "mimetype": "image/png", "thumbnail_url": "mxc://bark.lgbt/rqpOLhmTFquYDIMiISrdRFTt", "thumbnail_info": {"w": 256, "h": 256, "size": 145697, "mimetype": "image/png"}}, "msgtype": "m.sticker", "id": "tg-1252197925602197521", "net.maunium.telegram.sticker": {"pack": {"id": "1252197925602197505", "short_name": "QuelvhartheDragon"}, "id": "1252197925602197521", "emoticons": ["❤"]}}, {"body": "🖤", "url": "mxc://bark.lgbt/ajZWmCwitEYMuPOGNAPYkDBv", "info": {"w": 256, "h": 256, "size": 181833, "mimetype": "image/png", "thumbnail_url": "mxc://bark.lgbt/ajZWmCwitEYMuPOGNAPYkDBv", "thumbnail_info": {"w": 256, "h": 256, "size": 181833, "mimetype": "image/png"}}, "msgtype": "m.sticker", "id": "tg-1252197925602197522", "net.maunium.telegram.sticker": {"pack": {"id": "1252197925602197505", "short_name": "QuelvhartheDragon"}, "id": "1252197925602197522", "emoticons": ["🖤"]}}, {"body": "❕", "url": "mxc://bark.lgbt/ZZvBCDAGaKbnDcStrZpcALSu", "info": {"w": 256, "h": 256, "size": 190456, "mimetype": "image/png", "thumbnail_url": "mxc://bark.lgbt/ZZvBCDAGaKbnDcStrZpcALSu", "thumbnail_info": {"w": 256, "h": 256, "size": 190456, "mimetype": "image/png"}}, "msgtype": "m.sticker", "id": "tg-1252197925602197545", "net.maunium.telegram.sticker": {"pack": {"id": "1252197925602197505", "short_name": "QuelvhartheDragon"}, "id": "1252197925602197545", "emoticons": ["❕"]}}, {"body": "❕", "url": "mxc://bark.lgbt/ZMFPqIsxjtTcxTCINfutpWxx", "info": {"w": 256, "h": 256, "size": 165402, "mimetype": "image/png", "thumbnail_url": "mxc://bark.lgbt/ZMFPqIsxjtTcxTCINfutpWxx", "thumbnail_info": {"w": 256, "h": 256, "size": 165402, "mimetype": "image/png"}}, "msgtype": "m.sticker", "id": "tg-1252197925602197525", "net.maunium.telegram.sticker": {"pack": {"id": "1252197925602197505", "short_name": "QuelvhartheDragon"}, "id": "1252197925602197525", "emoticons": ["❕"]}}, {"body": "⁉️", "url": "mxc://bark.lgbt/FdbkaGibpQjklGNnsEOtraQF", "info": {"w": 256, "h": 256, "size": 109682, "mimetype": "image/png", "thumbnail_url": "mxc://bark.lgbt/FdbkaGibpQjklGNnsEOtraQF", "thumbnail_info": {"w": 256, "h": 256, "size": 109682, "mimetype": "image/png"}}, "msgtype": "m.sticker", "id": "tg-1252197925602197526", "net.maunium.telegram.sticker": {"pack": {"id": "1252197925602197505", "short_name": "QuelvhartheDragon"}, "id": "1252197925602197526", "emoticons": ["⁉"]}}, {"body": "🍖", "url": "mxc://bark.lgbt/MquIGaRyzafgEClNJHsiSAbT", "info": {"w": 256, "h": 256, "size": 161183, "mimetype": "image/png", "thumbnail_url": "mxc://bark.lgbt/MquIGaRyzafgEClNJHsiSAbT", "thumbnail_info": {"w": 256, "h": 256, "size": 161183, "mimetype": "image/png"}}, "msgtype": "m.sticker", "id": "tg-1252197925602197516", "net.maunium.telegram.sticker": {"pack": {"id": "1252197925602197505", "short_name": "QuelvhartheDragon"}, "id": "1252197925602197516", "emoticons": ["🍖"]}}, {"body": "🍣", "url": "mxc://bark.lgbt/dSlHHigZOXlIehNzlUtHLoXh", "info": {"w": 256, "h": 256, "size": 164739, "mimetype": "image/png", "thumbnail_url": "mxc://bark.lgbt/dSlHHigZOXlIehNzlUtHLoXh", "thumbnail_info": {"w": 256, "h": 256, "size": 164739, "mimetype": "image/png"}}, "msgtype": "m.sticker", "id": "tg-1252197925602197595", "net.maunium.telegram.sticker": {"pack": {"id": "1252197925602197505", "short_name": "QuelvhartheDragon"}, "id": "1252197925602197595", "emoticons": ["🍟", "🍖", "🍣", "🍕", "🍔", "🌮", "🌭"]}}, {"body": "🍪", "url": "mxc://bark.lgbt/IqEpkYgwdAxadROcLpRfsRCf", "info": {"w": 256, "h": 256, "size": 180515, "mimetype": "image/png", "thumbnail_url": "mxc://bark.lgbt/IqEpkYgwdAxadROcLpRfsRCf", "thumbnail_info": {"w": 256, "h": 256, "size": 180515, "mimetype": "image/png"}}, "msgtype": "m.sticker", "id": "tg-1252197925602197527", "net.maunium.telegram.sticker": {"pack": {"id": "1252197925602197505", "short_name": "QuelvhartheDragon"}, "id": "1252197925602197527", "emoticons": ["🍪"]}}, {"body": "☕️", "url": "mxc://bark.lgbt/XHcFGCLcDRjGkPezsxCOCHIK", "info": {"w": 256, "h": 256, "size": 160103, "mimetype": "image/png", "thumbnail_url": "mxc://bark.lgbt/XHcFGCLcDRjGkPezsxCOCHIK", "thumbnail_info": {"w": 256, "h": 256, "size": 160103, "mimetype": "image/png"}}, "msgtype": "m.sticker", "id": "tg-1252197925602197515", "net.maunium.telegram.sticker": {"pack": {"id": "1252197925602197505", "short_name": "QuelvhartheDragon"}, "id": "1252197925602197515", "emoticons": ["☕"]}}, {"body": "🍣", "url": "mxc://bark.lgbt/haKKLWNnkuPfxpqkcnHChxKT", "info": {"w": 256, "h": 256, "size": 146873, "mimetype": "image/png", "thumbnail_url": "mxc://bark.lgbt/haKKLWNnkuPfxpqkcnHChxKT", "thumbnail_info": {"w": 256, "h": 256, "size": 146873, "mimetype": "image/png"}}, "msgtype": "m.sticker", "id": "tg-1252197925602197539", "net.maunium.telegram.sticker": {"pack": {"id": "1252197925602197505", "short_name": "QuelvhartheDragon"}, "id": "1252197925602197539", "emoticons": ["🍣"]}}, {"body": "🤺", "url": "mxc://bark.lgbt/HpHKazThhFLMEgrwCZnZkXMg", "info": {"w": 256, "h": 256, "size": 201101, "mimetype": "image/png", "thumbnail_url": "mxc://bark.lgbt/HpHKazThhFLMEgrwCZnZkXMg", "thumbnail_info": {"w": 256, "h": 256, "size": 201101, "mimetype": "image/png"}}, "msgtype": "m.sticker", "id": "tg-1252197925602197585", "net.maunium.telegram.sticker": {"pack": {"id": "1252197925602197505", "short_name": "QuelvhartheDragon"}, "id": "1252197925602197585", "emoticons": ["🤺"]}}, {"body": "🎼", "url": "mxc://bark.lgbt/XgglRUYzsXRjbEgynDoHoxQY", "info": {"w": 256, "h": 256, "size": 231975, "mimetype": "image/png", "thumbnail_url": "mxc://bark.lgbt/XgglRUYzsXRjbEgynDoHoxQY", "thumbnail_info": {"w": 256, "h": 256, "size": 231975, "mimetype": "image/png"}}, "msgtype": "m.sticker", "id": "tg-1252197925602197529", "net.maunium.telegram.sticker": {"pack": {"id": "1252197925602197505", "short_name": "QuelvhartheDragon"}, "id": "1252197925602197529", "emoticons": ["🎼"]}}, {"body": "😁", "url": "mxc://bark.lgbt/hUDMLgpVTytqujBkyoaNtqhi", "info": {"w": 256, "h": 256, "size": 192667, "mimetype": "image/png", "thumbnail_url": "mxc://bark.lgbt/hUDMLgpVTytqujBkyoaNtqhi", "thumbnail_info": {"w": 256, "h": 256, "size": 192667, "mimetype": "image/png"}}, "msgtype": "m.sticker", "id": "tg-1252197925602197533", "net.maunium.telegram.sticker": {"pack": {"id": "1252197925602197505", "short_name": "QuelvhartheDragon"}, "id": "1252197925602197533", "emoticons": ["😁"]}}, {"body": "💧", "url": "mxc://bark.lgbt/EuWGCizdTySqgSWbuCGkEBPA", "info": {"w": 256, "h": 256, "size": 148041, "mimetype": "image/png", "thumbnail_url": "mxc://bark.lgbt/EuWGCizdTySqgSWbuCGkEBPA", "thumbnail_info": {"w": 256, "h": 256, "size": 148041, "mimetype": "image/png"}}, "msgtype": "m.sticker", "id": "tg-1252197925602197530", "net.maunium.telegram.sticker": {"pack": {"id": "1252197925602197505", "short_name": "QuelvhartheDragon"}, "id": "1252197925602197530", "emoticons": ["💧"]}}, {"body": "🐉", "url": "mxc://bark.lgbt/cCJsFylbrJTXtZjGrzxQPhIu", "info": {"w": 256, "h": 256, "size": 241003, "mimetype": "image/png", "thumbnail_url": "mxc://bark.lgbt/cCJsFylbrJTXtZjGrzxQPhIu", "thumbnail_info": {"w": 256, "h": 256, "size": 241003, "mimetype": "image/png"}}, "msgtype": "m.sticker", "id": "tg-1252197925602197603", "net.maunium.telegram.sticker": {"pack": {"id": "1252197925602197505", "short_name": "QuelvhartheDragon"}, "id": "1252197925602197603", "emoticons": ["🐉"]}}, {"body": "🧸", "url": "mxc://bark.lgbt/IhHKUVgJVPoFpiZIPtFfwFsZ", "info": {"w": 256, "h": 256, "size": 193762, "mimetype": "image/png", "thumbnail_url": "mxc://bark.lgbt/IhHKUVgJVPoFpiZIPtFfwFsZ", "thumbnail_info": {"w": 256, "h": 256, "size": 193762, "mimetype": "image/png"}}, "msgtype": "m.sticker", "id": "tg-1252197925602197607", "net.maunium.telegram.sticker": {"pack": {"id": "1252197925602197505", "short_name": "QuelvhartheDragon"}, "id": "1252197925602197607", "emoticons": ["🧸"]}}, {"body": "🛋", "url": "mxc://bark.lgbt/HnhyWebkBoMaOzenehGUrxxk", "info": {"w": 256, "h": 256, "size": 115723, "mimetype": "image/png", "thumbnail_url": "mxc://bark.lgbt/HnhyWebkBoMaOzenehGUrxxk", "thumbnail_info": {"w": 256, "h": 256, "size": 115723, "mimetype": "image/png"}}, "msgtype": "m.sticker", "id": "tg-1252197925602197531", "net.maunium.telegram.sticker": {"pack": {"id": "1252197925602197505", "short_name": "QuelvhartheDragon"}, "id": "1252197925602197531", "emoticons": ["🛋"]}}, {"body": "🤖", "url": "mxc://bark.lgbt/JUQthXcyMNuROBGYitbaPEXG", "info": {"w": 256, "h": 256, "size": 192289, "mimetype": "image/png", "thumbnail_url": "mxc://bark.lgbt/JUQthXcyMNuROBGYitbaPEXG", "thumbnail_info": {"w": 256, "h": 256, "size": 192289, "mimetype": "image/png"}}, "msgtype": "m.sticker", "id": "tg-1252197925602197608", "net.maunium.telegram.sticker": {"pack": {"id": "1252197925602197505", "short_name": "QuelvhartheDragon"}, "id": "1252197925602197608", "emoticons": ["🤖"]}}, {"body": "😆", "url": "mxc://bark.lgbt/kVywgudteasJpuCHlQtbUaDs", "info": {"w": 256, "h": 256, "size": 179174, "mimetype": "image/png", "thumbnail_url": "mxc://bark.lgbt/kVywgudteasJpuCHlQtbUaDs", "thumbnail_info": {"w": 256, "h": 256, "size": 179174, "mimetype": "image/png"}}, "msgtype": "m.sticker", "id": "tg-1252197925602197532", "net.maunium.telegram.sticker": {"pack": {"id": "1252197925602197505", "short_name": "QuelvhartheDragon"}, "id": "1252197925602197532", "emoticons": ["😆"]}}, {"body": "🤗", "url": "mxc://bark.lgbt/aFpPHJoQeHXSWnWWwijWzanV", "info": {"w": 256, "h": 256, "size": 228907, "mimetype": "image/png", "thumbnail_url": "mxc://bark.lgbt/aFpPHJoQeHXSWnWWwijWzanV", "thumbnail_info": {"w": 256, "h": 256, "size": 228907, "mimetype": "image/png"}}, "msgtype": "m.sticker", "id": "tg-1252197925602197534", "net.maunium.telegram.sticker": {"pack": {"id": "1252197925602197505", "short_name": "QuelvhartheDragon"}, "id": "1252197925602197534", "emoticons": ["🤗"]}}, {"body": "💋", "url": "mxc://bark.lgbt/xGfQRNCyAqVTRSFrkFLpJQsr", "info": {"w": 256, "h": 256, "size": 122692, "mimetype": "image/png", "thumbnail_url": "mxc://bark.lgbt/xGfQRNCyAqVTRSFrkFLpJQsr", "thumbnail_info": {"w": 256, "h": 256, "size": 122692, "mimetype": "image/png"}}, "msgtype": "m.sticker", "id": "tg-1252197925602197536", "net.maunium.telegram.sticker": {"pack": {"id": "1252197925602197505", "short_name": "QuelvhartheDragon"}, "id": "1252197925602197536", "emoticons": ["💋"]}}, {"body": "😀", "url": "mxc://bark.lgbt/WzgmsjELNzhJjJgeQtSVQBUd", "info": {"w": 256, "h": 256, "size": 148088, "mimetype": "image/png", "thumbnail_url": "mxc://bark.lgbt/WzgmsjELNzhJjJgeQtSVQBUd", "thumbnail_info": {"w": 256, "h": 256, "size": 148088, "mimetype": "image/png"}}, "msgtype": "m.sticker", "id": "tg-1252197925602197537", "net.maunium.telegram.sticker": {"pack": {"id": "1252197925602197505", "short_name": "QuelvhartheDragon"}, "id": "1252197925602197537", "emoticons": ["😀"]}}, {"body": "😢", "url": "mxc://bark.lgbt/jCaBCReuNLrAnxvCPGjPpGDb", "info": {"w": 256, "h": 256, "size": 97569, "mimetype": "image/png", "thumbnail_url": "mxc://bark.lgbt/jCaBCReuNLrAnxvCPGjPpGDb", "thumbnail_info": {"w": 256, "h": 256, "size": 97569, "mimetype": "image/png"}}, "msgtype": "m.sticker", "id": "tg-1252197925602197535", "net.maunium.telegram.sticker": {"pack": {"id": "1252197925602197505", "short_name": "QuelvhartheDragon"}, "id": "1252197925602197535", "emoticons": ["😢"]}}, {"body": "🐶", "url": "mxc://bark.lgbt/NkzHEjqIIBlUWIKuzQFvFkMx", "info": {"w": 256, "h": 256, "size": 141021, "mimetype": "image/png", "thumbnail_url": "mxc://bark.lgbt/NkzHEjqIIBlUWIKuzQFvFkMx", "thumbnail_info": {"w": 256, "h": 256, "size": 141021, "mimetype": "image/png"}}, "msgtype": "m.sticker", "id": "tg-1252197925602197517", "net.maunium.telegram.sticker": {"pack": {"id": "1252197925602197505", "short_name": "QuelvhartheDragon"}, "id": "1252197925602197517", "emoticons": ["🐶"]}}, {"body": "🗣", "url": "mxc://bark.lgbt/crjTsnJbcWbXgmAzGDRjhiTk", "info": {"w": 256, "h": 256, "size": 189660, "mimetype": "image/png", "thumbnail_url": "mxc://bark.lgbt/crjTsnJbcWbXgmAzGDRjhiTk", "thumbnail_info": {"w": 256, "h": 256, "size": 189660, "mimetype": "image/png"}}, "msgtype": "m.sticker", "id": "tg-1252197925602197590", "net.maunium.telegram.sticker": {"pack": {"id": "1252197925602197505", "short_name": "QuelvhartheDragon"}, "id": "1252197925602197590", "emoticons": ["🗣"]}}, {"body": "🥚", "url": "mxc://bark.lgbt/YIqDffJBIDkZPKUxMtYFrWhs", "info": {"w": 256, "h": 256, "size": 100924, "mimetype": "image/png", "thumbnail_url": "mxc://bark.lgbt/YIqDffJBIDkZPKUxMtYFrWhs", "thumbnail_info": {"w": 256, "h": 256, "size": 100924, "mimetype": "image/png"}}, "msgtype": "m.sticker", "id": "tg-1252197925602197604", "net.maunium.telegram.sticker": {"pack": {"id": "1252197925602197505", "short_name": "QuelvhartheDragon"}, "id": "1252197925602197604", "emoticons": ["🥚"]}}, {"body": "🎂", "url": "mxc://bark.lgbt/EIHbZOyzkVYwfXnJhJUysSKY", "info": {"w": 256, "h": 256, "size": 186369, "mimetype": "image/png", "thumbnail_url": "mxc://bark.lgbt/EIHbZOyzkVYwfXnJhJUysSKY", "thumbnail_info": {"w": 256, "h": 256, "size": 186369, "mimetype": "image/png"}}, "msgtype": "m.sticker", "id": "tg-1252197925602197605", "net.maunium.telegram.sticker": {"pack": {"id": "1252197925602197505", "short_name": "QuelvhartheDragon"}, "id": "1252197925602197605", "emoticons": ["🎂"]}}, {"body": "🥺", "url": "mxc://bark.lgbt/vooBvkQDcnfXSmvmqbgVLvQR", "info": {"w": 256, "h": 256, "size": 153329, "mimetype": "image/png", "thumbnail_url": "mxc://bark.lgbt/vooBvkQDcnfXSmvmqbgVLvQR", "thumbnail_info": {"w": 256, "h": 256, "size": 153329, "mimetype": "image/png"}}, "msgtype": "m.sticker", "id": "tg-1252197925602197606", "net.maunium.telegram.sticker": {"pack": {"id": "1252197925602197505", "short_name": "QuelvhartheDragon"}, "id": "1252197925602197606", "emoticons": ["🥺"]}}, {"body": "💣", "url": "mxc://bark.lgbt/aXRIAvrlUgweWWKZVtBAcvxu", "info": {"w": 256, "h": 256, "size": 198219, "mimetype": "image/png", "thumbnail_url": "mxc://bark.lgbt/aXRIAvrlUgweWWKZVtBAcvxu", "thumbnail_info": {"w": 256, "h": 256, "size": 198219, "mimetype": "image/png"}}, "msgtype": "m.sticker", "id": "tg-1252197925602197538", "net.maunium.telegram.sticker": {"pack": {"id": "1252197925602197505", "short_name": "QuelvhartheDragon"}, "id": "1252197925602197538", "emoticons": ["💣"]}}, {"body": "⛔️", "url": "mxc://bark.lgbt/YJZsufRklFomCdNzOMpHyYZF", "info": {"w": 256, "h": 256, "size": 209884, "mimetype": "image/png", "thumbnail_url": "mxc://bark.lgbt/YJZsufRklFomCdNzOMpHyYZF", "thumbnail_info": {"w": 256, "h": 256, "size": 209884, "mimetype": "image/png"}}, "msgtype": "m.sticker", "id": "tg-1252197925602197528", "net.maunium.telegram.sticker": {"pack": {"id": "1252197925602197505", "short_name": "QuelvhartheDragon"}, "id": "1252197925602197528", "emoticons": ["⛔"]}}, {"body": "😡", "url": "mxc://bark.lgbt/eLCRTNFrIQczwDKpTJugaWeR", "info": {"w": 256, "h": 256, "size": 197719, "mimetype": "image/png", "thumbnail_url": "mxc://bark.lgbt/eLCRTNFrIQczwDKpTJugaWeR", "thumbnail_info": {"w": 256, "h": 256, "size": 197719, "mimetype": "image/png"}}, "msgtype": "m.sticker", "id": "tg-1252197925602197540", "net.maunium.telegram.sticker": {"pack": {"id": "1252197925602197505", "short_name": "QuelvhartheDragon"}, "id": "1252197925602197540", "emoticons": ["😡"]}}, {"body": "❌", "url": "mxc://bark.lgbt/JXwKnMNOIpHLVWuzFZqjCMZY", "info": {"w": 256, "h": 256, "size": 216743, "mimetype": "image/png", "thumbnail_url": "mxc://bark.lgbt/JXwKnMNOIpHLVWuzFZqjCMZY", "thumbnail_info": {"w": 256, "h": 256, "size": 216743, "mimetype": "image/png"}}, "msgtype": "m.sticker", "id": "tg-1252197925602197584", "net.maunium.telegram.sticker": {"pack": {"id": "1252197925602197505", "short_name": "QuelvhartheDragon"}, "id": "1252197925602197584", "emoticons": ["❌"]}}, {"body": "🏊‍♂️", "url": "mxc://bark.lgbt/aPnpKMyTBKkGhObmwFVSPpdW", "info": {"w": 256, "h": 256, "size": 163999, "mimetype": "image/png", "thumbnail_url": "mxc://bark.lgbt/aPnpKMyTBKkGhObmwFVSPpdW", "thumbnail_info": {"w": 256, "h": 256, "size": 163999, "mimetype": "image/png"}}, "msgtype": "m.sticker", "id": "tg-1252197925602197586", "net.maunium.telegram.sticker": {"pack": {"id": "1252197925602197505", "short_name": "QuelvhartheDragon"}, "id": "1252197925602197586", "emoticons": ["🏊‍♂"]}}, {"body": "🗑", "url": "mxc://bark.lgbt/xXFftcIdthOLkxNnRQtdRMKv", "info": {"w": 256, "h": 256, "size": 211524, "mimetype": "image/png", "thumbnail_url": "mxc://bark.lgbt/xXFftcIdthOLkxNnRQtdRMKv", "thumbnail_info": {"w": 256, "h": 256, "size": 211524, "mimetype": "image/png"}}, "msgtype": "m.sticker", "id": "tg-1252197925602197589", "net.maunium.telegram.sticker": {"pack": {"id": "1252197925602197505", "short_name": "QuelvhartheDragon"}, "id": "1252197925602197589", "emoticons": ["🗑"]}}, {"body": "✂️", "url": "mxc://bark.lgbt/YerUIeHvdmwBfVdpBqahlgqB", "info": {"w": 256, "h": 256, "size": 142219, "mimetype": "image/png", "thumbnail_url": "mxc://bark.lgbt/YerUIeHvdmwBfVdpBqahlgqB", "thumbnail_info": {"w": 256, "h": 256, "size": 142219, "mimetype": "image/png"}}, "msgtype": "m.sticker", "id": "tg-1252197925602197591", "net.maunium.telegram.sticker": {"pack": {"id": "1252197925602197505", "short_name": "QuelvhartheDragon"}, "id": "1252197925602197591", "emoticons": ["✂", "🖍"]}}, {"body": "🖍", "url": "mxc://bark.lgbt/oISmTbUbyweuBpqEZqFMTQJp", "info": {"w": 256, "h": 256, "size": 185785, "mimetype": "image/png", "thumbnail_url": "mxc://bark.lgbt/oISmTbUbyweuBpqEZqFMTQJp", "thumbnail_info": {"w": 256, "h": 256, "size": 185785, "mimetype": "image/png"}}, "msgtype": "m.sticker", "id": "tg-1252197925602197592", "net.maunium.telegram.sticker": {"pack": {"id": "1252197925602197505", "short_name": "QuelvhartheDragon"}, "id": "1252197925602197592", "emoticons": ["👑", "🖍"]}}, {"body": "😤", "url": "mxc://bark.lgbt/DCnOcoDmPjHGdBvRpHtniDmX", "info": {"w": 256, "h": 256, "size": 163096, "mimetype": "image/png", "thumbnail_url": "mxc://bark.lgbt/DCnOcoDmPjHGdBvRpHtniDmX", "thumbnail_info": {"w": 256, "h": 256, "size": 163096, "mimetype": "image/png"}}, "msgtype": "m.sticker", "id": "tg-1252197925602197593", "net.maunium.telegram.sticker": {"pack": {"id": "1252197925602197505", "short_name": "QuelvhartheDragon"}, "id": "1252197925602197593", "emoticons": ["😤"]}}, {"body": "♟", "url": "mxc://bark.lgbt/FzyczoDuVHppdgJrkNkLuRCR", "info": {"w": 256, "h": 256, "size": 257517, "mimetype": "image/png", "thumbnail_url": "mxc://bark.lgbt/FzyczoDuVHppdgJrkNkLuRCR", "thumbnail_info": {"w": 256, "h": 256, "size": 257517, "mimetype": "image/png"}}, "msgtype": "m.sticker", "id": "tg-1252197925602197594", "net.maunium.telegram.sticker": {"pack": {"id": "1252197925602197505", "short_name": "QuelvhartheDragon"}, "id": "1252197925602197594", "emoticons": ["♟"]}}, {"body": "🤫", "url": "mxc://bark.lgbt/qHnkkdgkGtRCITKQPRAORGAR", "info": {"w": 256, "h": 256, "size": 150848, "mimetype": "image/png", "thumbnail_url": "mxc://bark.lgbt/qHnkkdgkGtRCITKQPRAORGAR", "thumbnail_info": {"w": 256, "h": 256, "size": 150848, "mimetype": "image/png"}}, "msgtype": "m.sticker", "id": "tg-1252197925602197596", "net.maunium.telegram.sticker": {"pack": {"id": "1252197925602197505", "short_name": "QuelvhartheDragon"}, "id": "1252197925602197596", "emoticons": ["🤫"]}}, {"body": "🥏", "url": "mxc://bark.lgbt/YZSkJjCFiIZJYWTTZLebtWDY", "info": {"w": 256, "h": 256, "size": 192037, "mimetype": "image/png", "thumbnail_url": "mxc://bark.lgbt/YZSkJjCFiIZJYWTTZLebtWDY", "thumbnail_info": {"w": 256, "h": 256, "size": 192037, "mimetype": "image/png"}}, "msgtype": "m.sticker", "id": "tg-1252197925602197597", "net.maunium.telegram.sticker": {"pack": {"id": "1252197925602197505", "short_name": "QuelvhartheDragon"}, "id": "1252197925602197597", "emoticons": ["🥏"]}}, {"body": "🍆", "url": "mxc://bark.lgbt/AjylaamkMkKkXqzHGapfdGUo", "info": {"w": 256, "h": 256, "size": 181189, "mimetype": "image/png", "thumbnail_url": "mxc://bark.lgbt/AjylaamkMkKkXqzHGapfdGUo", "thumbnail_info": {"w": 256, "h": 256, "size": 181189, "mimetype": "image/png"}}, "msgtype": "m.sticker", "id": "tg-1252197925602197510", "net.maunium.telegram.sticker": {"pack": {"id": "1252197925602197505", "short_name": "QuelvhartheDragon"}, "id": "1252197925602197510", "emoticons": ["🍆"]}}, {"body": "🗣", "url": "mxc://bark.lgbt/BMMzVnlgMKVItISbFWuAYtXY", "info": {"w": 256, "h": 256, "size": 195895, "mimetype": "image/png", "thumbnail_url": "mxc://bark.lgbt/BMMzVnlgMKVItISbFWuAYtXY", "thumbnail_info": {"w": 256, "h": 256, "size": 195895, "mimetype": "image/png"}}, "msgtype": "m.sticker", "id": "tg-1252197925602197513", "net.maunium.telegram.sticker": {"pack": {"id": "1252197925602197505", "short_name": "QuelvhartheDragon"}, "id": "1252197925602197513", "emoticons": ["🗣"]}}, {"body": "🤡", "url": "mxc://bark.lgbt/nsyvdsnNoixOGMbRXnzqxbiT", "info": {"w": 256, "h": 256, "size": 155374, "mimetype": "image/png", "thumbnail_url": "mxc://bark.lgbt/nsyvdsnNoixOGMbRXnzqxbiT", "thumbnail_info": {"w": 256, "h": 256, "size": 155374, "mimetype": "image/png"}}, "msgtype": "m.sticker", "id": "tg-1252197925602197512", "net.maunium.telegram.sticker": {"pack": {"id": "1252197925602197505", "short_name": "QuelvhartheDragon"}, "id": "1252197925602197512", "emoticons": ["🤡"]}}, {"body": "🎅", "url": "mxc://bark.lgbt/vXCXANFliIXCvmbmyVWiFwkm", "info": {"w": 256, "h": 255, "size": 245335, "mimetype": "image/png", "thumbnail_url": "mxc://bark.lgbt/vXCXANFliIXCvmbmyVWiFwkm", "thumbnail_info": {"w": 256, "h": 255, "size": 245335, "mimetype": "image/png"}}, "msgtype": "m.sticker", "id": "tg-1252197925602197546", "net.maunium.telegram.sticker": {"pack": {"id": "1252197925602197505", "short_name": "QuelvhartheDragon"}, "id": "1252197925602197546", "emoticons": ["🎅"]}}, {"body": "💓", "url": "mxc://bark.lgbt/QTNVEPwvDpRBjqUyjuwJvPBK", "info": {"w": 256, "h": 256, "size": 185556, "mimetype": "image/png", "thumbnail_url": "mxc://bark.lgbt/QTNVEPwvDpRBjqUyjuwJvPBK", "thumbnail_info": {"w": 256, "h": 256, "size": 185556, "mimetype": "image/png"}}, "msgtype": "m.sticker", "id": "tg-1252197925602197523", "net.maunium.telegram.sticker": {"pack": {"id": "1252197925602197505", "short_name": "QuelvhartheDragon"}, "id": "1252197925602197523", "emoticons": ["💓"]}}, {"body": "🍑", "url": "mxc://bark.lgbt/SQXZHXmjjzadDQAfwRmEgYgR", "info": {"w": 256, "h": 256, "size": 178757, "mimetype": "image/png", "thumbnail_url": "mxc://bark.lgbt/SQXZHXmjjzadDQAfwRmEgYgR", "thumbnail_info": {"w": 256, "h": 256, "size": 178757, "mimetype": "image/png"}}, "msgtype": "m.sticker", "id": "tg-1252197925602197541", "net.maunium.telegram.sticker": {"pack": {"id": "1252197925602197505", "short_name": "QuelvhartheDragon"}, "id": "1252197925602197541", "emoticons": ["🍑"]}}, {"body": "💰", "url": "mxc://bark.lgbt/AXgVxrdWhJLBCacYQLvNnkkv", "info": {"w": 256, "h": 256, "size": 222908, "mimetype": "image/png", "thumbnail_url": "mxc://bark.lgbt/AXgVxrdWhJLBCacYQLvNnkkv", "thumbnail_info": {"w": 256, "h": 256, "size": 222908, "mimetype": "image/png"}}, "msgtype": "m.sticker", "id": "tg-1252197925602197542", "net.maunium.telegram.sticker": {"pack": {"id": "1252197925602197505", "short_name": "QuelvhartheDragon"}, "id": "1252197925602197542", "emoticons": ["💰", "💦"]}}, {"body": "🍭", "url": "mxc://bark.lgbt/QTJRcBZMICMYmSLGUDvGEANF", "info": {"w": 256, "h": 256, "size": 185862, "mimetype": "image/png", "thumbnail_url": "mxc://bark.lgbt/QTJRcBZMICMYmSLGUDvGEANF", "thumbnail_info": {"w": 256, "h": 256, "size": 185862, "mimetype": "image/png"}}, "msgtype": "m.sticker", "id": "tg-1252197925602197543", "net.maunium.telegram.sticker": {"pack": {"id": "1252197925602197505", "short_name": "QuelvhartheDragon"}, "id": "1252197925602197543", "emoticons": ["🍭"]}}, {"body": "🍭", "url": "mxc://bark.lgbt/SaeEaYeFytQrKkihSbhydFkx", "info": {"w": 256, "h": 256, "size": 159654, "mimetype": "image/png", "thumbnail_url": "mxc://bark.lgbt/SaeEaYeFytQrKkihSbhydFkx", "thumbnail_info": {"w": 256, "h": 256, "size": 159654, "mimetype": "image/png"}}, "msgtype": "m.sticker", "id": "tg-1252197925602197544", "net.maunium.telegram.sticker": {"pack": {"id": "1252197925602197505", "short_name": "QuelvhartheDragon"}, "id": "1252197925602197544", "emoticons": ["🍭"]}}, {"body": "🍑", "url": "mxc://bark.lgbt/AEfuTGAYSLDNAiwtKWBxZzVd", "info": {"w": 256, "h": 256, "size": 207397, "mimetype": "image/png", "thumbnail_url": "mxc://bark.lgbt/AEfuTGAYSLDNAiwtKWBxZzVd", "thumbnail_info": {"w": 256, "h": 256, "size": 207397, "mimetype": "image/png"}}, "msgtype": "m.sticker", "id": "tg-1252197925602197578", "net.maunium.telegram.sticker": {"pack": {"id": "1252197925602197505", "short_name": "QuelvhartheDragon"}, "id": "1252197925602197578", "emoticons": ["🍑"]}}, {"body": "🍑", "url": "mxc://bark.lgbt/MldkjlyBdDayeVcksAAiUaux", "info": {"w": 256, "h": 256, "size": 165727, "mimetype": "image/png", "thumbnail_url": "mxc://bark.lgbt/MldkjlyBdDayeVcksAAiUaux", "thumbnail_info": {"w": 256, "h": 256, "size": 165727, "mimetype": "image/png"}}, "msgtype": "m.sticker", "id": "tg-1252197925602197579", "net.maunium.telegram.sticker": {"pack": {"id": "1252197925602197505", "short_name": "QuelvhartheDragon"}, "id": "1252197925602197579", "emoticons": ["🍑"]}}, {"body": "🍆", "url": "mxc://bark.lgbt/cVBbYaYlQskkvymraYvMVlaS", "info": {"w": 256, "h": 256, "size": 153720, "mimetype": "image/png", "thumbnail_url": "mxc://bark.lgbt/cVBbYaYlQskkvymraYvMVlaS", "thumbnail_info": {"w": 256, "h": 256, "size": 153720, "mimetype": "image/png"}}, "msgtype": "m.sticker", "id": "tg-1252197925602197580", "net.maunium.telegram.sticker": {"pack": {"id": "1252197925602197505", "short_name": "QuelvhartheDragon"}, "id": "1252197925602197580", "emoticons": ["🍆"]}}, {"body": "☯️", "url": "mxc://bark.lgbt/lxHDWSpEMYRhkdWUenqnjEva", "info": {"w": 256, "h": 256, "size": 204229, "mimetype": "image/png", "thumbnail_url": "mxc://bark.lgbt/lxHDWSpEMYRhkdWUenqnjEva", "thumbnail_info": {"w": 256, "h": 256, "size": 204229, "mimetype": "image/png"}}, "msgtype": "m.sticker", "id": "tg-1252197925602197581", "net.maunium.telegram.sticker": {"pack": {"id": "1252197925602197505", "short_name": "QuelvhartheDragon"}, "id": "1252197925602197581", "emoticons": ["☯"]}}, {"body": "🍒", "url": "mxc://bark.lgbt/ZsQPdVyTCqcBoPQhMmQeBtHA", "info": {"w": 256, "h": 256, "size": 191495, "mimetype": "image/png", "thumbnail_url": "mxc://bark.lgbt/ZsQPdVyTCqcBoPQhMmQeBtHA", "thumbnail_info": {"w": 256, "h": 256, "size": 191495, "mimetype": "image/png"}}, "msgtype": "m.sticker", "id": "tg-1252197925602197582", "net.maunium.telegram.sticker": {"pack": {"id": "1252197925602197505", "short_name": "QuelvhartheDragon"}, "id": "1252197925602197582", "emoticons": ["🍆", "🍒"]}}, {"body": "🍆", "url": "mxc://bark.lgbt/YKXWanJAHjEgCQNkARzcbRgF", "info": {"w": 256, "h": 256, "size": 206106, "mimetype": "image/png", "thumbnail_url": "mxc://bark.lgbt/YKXWanJAHjEgCQNkARzcbRgF", "thumbnail_info": {"w": 256, "h": 256, "size": 206106, "mimetype": "image/png"}}, "msgtype": "m.sticker", "id": "tg-1252197925602197583", "net.maunium.telegram.sticker": {"pack": {"id": "1252197925602197505", "short_name": "QuelvhartheDragon"}, "id": "1252197925602197583", "emoticons": ["🍆", "🍒"]}}, {"body": "🎨", "url": "mxc://bark.lgbt/qmjaYPaoGNIPUJbHNMCKlmhv", "info": {"w": 256, "h": 256, "size": 225969, "mimetype": "image/png", "thumbnail_url": "mxc://bark.lgbt/qmjaYPaoGNIPUJbHNMCKlmhv", "thumbnail_info": {"w": 256, "h": 256, "size": 225969, "mimetype": "image/png"}}, "msgtype": "m.sticker", "id": "tg-1252197925602197524", "net.maunium.telegram.sticker": {"pack": {"id": "1252197925602197505", "short_name": "QuelvhartheDragon"}, "id": "1252197925602197524", "emoticons": ["🎨"]}}, {"body": "🥰", "url": "mxc://bark.lgbt/HKjHatjoCIHpwBvoySluSoIn", "info": {"w": 256, "h": 256, "size": 470591, "mimetype": "image/png", "thumbnail_url": "mxc://bark.lgbt/HKjHatjoCIHpwBvoySluSoIn", "thumbnail_info": {"w": 256, "h": 256, "size": 470591, "mimetype": "image/png"}}, "msgtype": "m.sticker", "id": "tg-4976752307237552596", "net.maunium.telegram.sticker": {"pack": {"id": "1252197925602197505", "short_name": "QuelvhartheDragon"}, "id": "4976752307237552596", "emoticons": ["🤗", "🥰"]}}, {"body": "😒", "url": "mxc://bark.lgbt/WTftcTSHrrKexVmLzbDmptYu", "info": {"w": 256, "h": 256, "size": 308581, "mimetype": "image/png", "thumbnail_url": "mxc://bark.lgbt/WTftcTSHrrKexVmLzbDmptYu", "thumbnail_info": {"w": 256, "h": 256, "size": 308581, "mimetype": "image/png"}}, "msgtype": "m.sticker", "id": "tg-4976543232524550879", "net.maunium.telegram.sticker": {"pack": {"id": "1252197925602197505", "short_name": "QuelvhartheDragon"}, "id": "4976543232524550879", "emoticons": ["😒"]}}, {"body": "🛁", "url": "mxc://bark.lgbt/dahufdvDbSYIzJMRLNdETzZu", "info": {"w": 256, "h": 256, "size": 462414, "mimetype": "image/png", "thumbnail_url": "mxc://bark.lgbt/dahufdvDbSYIzJMRLNdETzZu", "thumbnail_info": {"w": 256, "h": 256, "size": 462414, "mimetype": "image/png"}}, "msgtype": "m.sticker", "id": "tg-4978803454769103206", "net.maunium.telegram.sticker": {"pack": {"id": "1252197925602197505", "short_name": "QuelvhartheDragon"}, "id": "4978803454769103206", "emoticons": ["🛁"]}}, {"body": "🤩", "url": "mxc://bark.lgbt/LMPlSLPrPTkIhKJRzLwScrVS", "info": {"w": 256, "h": 256, "size": 349435, "mimetype": "image/png", "thumbnail_url": "mxc://bark.lgbt/LMPlSLPrPTkIhKJRzLwScrVS", "thumbnail_info": {"w": 256, "h": 256, "size": 349435, "mimetype": "image/png"}}, "msgtype": "m.sticker", "id": "tg-4978843290590773562", "net.maunium.telegram.sticker": {"pack": {"id": "1252197925602197505", "short_name": "QuelvhartheDragon"}, "id": "4978843290590773562", "emoticons": ["🤩", "🕹"]}}, {"body": "🤨", "url": "mxc://bark.lgbt/TNAjmJxNCnWNDAHuOeObiLVS", "info": {"w": 256, "h": 256, "size": 300261, "mimetype": "image/png", "thumbnail_url": "mxc://bark.lgbt/TNAjmJxNCnWNDAHuOeObiLVS", "thumbnail_info": {"w": 256, "h": 256, "size": 300261, "mimetype": "image/png"}}, "msgtype": "m.sticker", "id": "tg-4978905717940420946", "net.maunium.telegram.sticker": {"pack": {"id": "1252197925602197505", "short_name": "QuelvhartheDragon"}, "id": "4978905717940420946", "emoticons": ["🤨", "🧑‍🔧"]}}, {"body": "😁", "url": "mxc://bark.lgbt/lcJrSZimSFqtfeFzFFQRodWH", "info": {"w": 256, "h": 256, "size": 328312, "mimetype": "image/png", "thumbnail_url": "mxc://bark.lgbt/lcJrSZimSFqtfeFzFFQRodWH", "thumbnail_info": {"w": 256, "h": 256, "size": 328312, "mimetype": "image/png"}}, "msgtype": "m.sticker", "id": "tg-4976801609167143299", "net.maunium.telegram.sticker": {"pack": {"id": "1252197925602197505", "short_name": "QuelvhartheDragon"}, "id": "4976801609167143299", "emoticons": ["😁", "🤩"]}}, {"body": "🎼", "url": "mxc://bark.lgbt/oXQDPTtniVODpBflQPdNsRxf", "info": {"w": 256, "h": 256, "size": 207432, "mimetype": "image/png", "thumbnail_url": "mxc://bark.lgbt/oXQDPTtniVODpBflQPdNsRxf", "thumbnail_info": {"w": 256, "h": 256, "size": 207432, "mimetype": "image/png"}}, "msgtype": "m.sticker", "id": "tg-4976524386208055612", "net.maunium.telegram.sticker": {"pack": {"id": "1252197925602197505", "short_name": "QuelvhartheDragon"}, "id": "4976524386208055612", "emoticons": ["🎼", "🎹"]}}, {"body": "👑", "url": "mxc://bark.lgbt/FAEXONBlhnsefcdmGimHPNXW", "info": {"w": 256, "h": 256, "size": 146984, "mimetype": "image/png", "thumbnail_url": "mxc://bark.lgbt/FAEXONBlhnsefcdmGimHPNXW", "thumbnail_info": {"w": 256, "h": 256, "size": 146984, "mimetype": "image/png"}}, "msgtype": "m.sticker", "id": "tg-1252197925602197518", "net.maunium.telegram.sticker": {"pack": {"id": "1252197925602197505", "short_name": "QuelvhartheDragon"}, "id": "1252197925602197518", "emoticons": ["👑"]}}]}